drug_evals/__init__.py
drug_evals/metrics.py
drug_evals-0.0.1.dist-info/METADATA
drug_evals-0.0.1.dist-info/WHEEL
drug_evals-0.0.1.dist-info/top_level.txt
drug_evals-0.0.1.dist-info/RECORD
