Metadata-Version: 2.1
Name: drug-evals
Version: 0.0.1
Summary: drug evalutions from QHGG
Home-page: http://null.null.null
Author: QHGG
Author-email: qhonearth@sjtu.edu.cn
Maintainer: QHGG
Maintainer-email: qhonearth@sjtu.edu.cn
License: MIT License
Platform: all
Classifier: Intended Audience :: Developers
Classifier: Operating System :: OS Independent
Classifier: Natural Language :: Chinese (Simplified)
Classifier: Programming Language :: Python
Classifier: Programming Language :: Python :: 2
Classifier: Programming Language :: Python :: 2.7
Classifier: Programming Language :: Python :: 3
Classifier: Programming Language :: Python :: 3.5
Classifier: Programming Language :: Python :: 3.6
Classifier: Programming Language :: Python :: 3.7
Classifier: Programming Language :: Python :: 3.8
Classifier: Topic :: Software Development :: Libraries
